WsseHeaders/AES.py
WsseHeaders/__init__.py
WsseHeaders/__main__.py
WsseHeaders/__version__.py
WsseHeaders/utilities.py
WsseHeaders/wsseheader.py
WsseHeaders-0.0.16.dist-info/AUTHORS.rst
WsseHeaders-0.0.16.dist-info/LICENSE
WsseHeaders-0.0.16.dist-info/METADATA
WsseHeaders-0.0.16.dist-info/WHEEL
WsseHeaders-0.0.16.dist-info/top_level.txt
WsseHeaders-0.0.16.dist-info/RECORD
