Metadata-Version: 2.1
Name: WsseHeaders
Version: 0.0.16
Summary: A package to generate WSSE Headers
Home-page: https://github.com/light-bringer/wsse-headers
Author: Debapriya Das
Author-email: yodebu@gmail.com
License: MIT
Keywords: WSSE Headers generation
Platform: UNKNOWN
Classifier: Development Status :: 3 - Alpha
Classifier: Intended Audience :: Developers
Classifier: Topic :: Software Development
Classifier: Programming Language :: Python :: 3
Classifier: License :: OSI Approved :: MIT License
Classifier: Operating System :: OS Independent
Requires-Python: >=3.0, <4
Requires-Dist: pycryptodome (>=3.7.0)
Requires-Dist: pytz (>=2018.5)
